blackduck_results/__init__.py
blackduck_results/find_projects.py
blackduck_results/risklibs.py
blackduck_results-1.0.14.dist-info/LICENSE
blackduck_results-1.0.14.dist-info/METADATA
blackduck_results-1.0.14.dist-info/WHEEL
blackduck_results-1.0.14.dist-info/entry_points.txt
blackduck_results-1.0.14.dist-info/top_level.txt
blackduck_results-1.0.14.dist-info/RECORD
