Metadata-Version: 2.1
Name: blackduck-results
Version: 1.0.14
Summary: Recursively traverse subprojects and summarize offending libraries in a format suitable for integration with other tools and human consumption.
Home-page: https://https://adc.github.trendmicro.com/fabioa/blackduck-results
Author: Fabio Arciniegas
Author-email: fabio_arciniegas@trendmicro.com
License: UNKNOWN
Platform: UNKNOWN
Requires-Python: >=3.6
Requires-Dist: blackduck
Requires-Dist: pandas
